tiamat/conf.py
tiamat/scripts.py
tiamat/version.py
tiamat/builder/init.py
tiamat/builder/pyinstaller.py
tiamat/builder/contracts/init.py
tiamat/package/dmg.py
tiamat/package/fpm.py
tiamat/package/init.py
tiamat/package/msi.py
tiamat/package/contracts/init.py
tiamat/tiamat/clean.py
tiamat/tiamat/cmdmod.py
tiamat/tiamat/data.py
tiamat/tiamat/init.py
tiamat/tiamat/make.py
tiamat/tiamat/post.py
tiamat/tool/pyinstaller/requirements.py
tiamat/tool/pyinstaller/runner.py
tiamat/tool/pyinstaller/spec.py
tiamat/virtualenv/builtin.py
tiamat/virtualenv/init.py
tiamat/virtualenv/pyenv.py
tiamat/virtualenv/pyvenv.py
tiamat/virtualenv/system.py
tiamat/virtualenv/venv.py
tiamat/virtualenv/virtualenv.py
tiamat/virtualenv/virtualenv3.py
tiamat/virtualenv/contracts/init.py
tiamat-8.0.0.dist-info/LICENSE
tiamat-8.0.0.dist-info/METADATA
tiamat-8.0.0.dist-info/WHEEL
tiamat-8.0.0.dist-info/entry_points.txt
tiamat-8.0.0.dist-info/top_level.txt
tiamat-8.0.0.dist-info/RECORD
