Metadata-Version: 2.1
Name: tiamat
Version: 8.0.0
Summary: Single binary builder for Python projects
Home-page: https://gitlab.com/saltstack/pop/tiamat
Author: 
Author-email: 
License: UNKNOWN
Platform: UNKNOWN
Classifier: Operating System :: OS Independent
Classifier: Programming Language :: Python
Classifier: Programming Language :: Python :: 3.9
Classifier: Programming Language :: Python :: 3.10
Classifier: Development Status :: 5 - Production/Stable
Requires-Python: >=3.9,!=3.10.0,!=3.10.1
License-File: LICENSE
Requires-Dist: dict-toolbox (>=2.2.0)
Requires-Dist: pop (>=14)
Requires-Dist: requests (>=2.21.0)
Requires-Dist: setuptools (>=50.3.0)
Requires-Dist: pop-config (>=9.0.0)
